torch_sparse_adamw/__init__.py
torch_sparse_adamw/sparse_adamw.py
torch_sparse_adamw-1.0.0.dist-info/LICENSE
torch_sparse_adamw-1.0.0.dist-info/METADATA
torch_sparse_adamw-1.0.0.dist-info/WHEEL
torch_sparse_adamw-1.0.0.dist-info/top_level.txt
torch_sparse_adamw-1.0.0.dist-info/RECORD
